CongLingdaoYiShenruXuexiQukuaiLianGongshiJizhi/README.md
CongLingdaoYiShenruXuexiQukuaiLianGongshiJizhi/__init__.py
CongLingdaoYiShenruXuexiQukuaiLianGongshiJizhi/__main__.py
CongLingdaoYiShenruXuexiQukuaiLianGongshiJizhi/file.epub
CongLingdaoYiShenruXuexiQukuaiLianGongshiJizhi/index.html
CongLingdaoYiShenruXuexiQukuaiLianGongshiJizhi/css/__init__.py
CongLingdaoYiShenruXuexiQukuaiLianGongshiJizhi/css/annotations.css
CongLingdaoYiShenruXuexiQukuaiLianGongshiJizhi/css/main.css
CongLingdaoYiShenruXuexiQukuaiLianGongshiJizhi/css/normalize.css
CongLingdaoYiShenruXuexiQukuaiLianGongshiJizhi/css/popup.css
CongLingdaoYiShenruXuexiQukuaiLianGongshiJizhi/font/__init__.py
CongLingdaoYiShenruXuexiQukuaiLianGongshiJizhi/font/fontello.eot
CongLingdaoYiShenruXuexiQukuaiLianGongshiJizhi/font/fontello.svg
CongLingdaoYiShenruXuexiQukuaiLianGongshiJizhi/font/fontello.ttf
CongLingdaoYiShenruXuexiQukuaiLianGongshiJizhi/font/fontello.woff
CongLingdaoYiShenruXuexiQukuaiLianGongshiJizhi/img/__init__.py
CongLingdaoYiShenruXuexiQukuaiLianGongshiJizhi/img/annotator-glyph-sprite.png
CongLingdaoYiShenruXuexiQukuaiLianGongshiJizhi/img/annotator-icon-sprite.png
CongLingdaoYiShenruXuexiQukuaiLianGongshiJizhi/img/apple-touch-icon.png
CongLingdaoYiShenruXuexiQukuaiLianGongshiJizhi/img/cancelfullscreen.png
CongLingdaoYiShenruXuexiQukuaiLianGongshiJizhi/img/close.png
CongLingdaoYiShenruXuexiQukuaiLianGongshiJizhi/img/fullscreen.png
CongLingdaoYiShenruXuexiQukuaiLianGongshiJizhi/img/loader.gif
CongLingdaoYiShenruXuexiQukuaiLianGongshiJizhi/img/menu-icon.png
CongLingdaoYiShenruXuexiQukuaiLianGongshiJizhi/img/save.png
CongLingdaoYiShenruXuexiQukuaiLianGongshiJizhi/img/saved.png
CongLingdaoYiShenruXuexiQukuaiLianGongshiJizhi/img/settings-s.png
CongLingdaoYiShenruXuexiQukuaiLianGongshiJizhi/img/settings.png
CongLingdaoYiShenruXuexiQukuaiLianGongshiJizhi/img/star.png
CongLingdaoYiShenruXuexiQukuaiLianGongshiJizhi/js/__init__.py
CongLingdaoYiShenruXuexiQukuaiLianGongshiJizhi/js/epub.js
cong_lingdao_yi_shenru_xuexi_qukuai_lian_gongshi_jizhi-2024.3.5.0.dist-info/METADATA
cong_lingdao_yi_shenru_xuexi_qukuai_lian_gongshi_jizhi-2024.3.5.0.dist-info/WHEEL
cong_lingdao_yi_shenru_xuexi_qukuai_lian_gongshi_jizhi-2024.3.5.0.dist-info/entry_points.txt
cong_lingdao_yi_shenru_xuexi_qukuai_lian_gongshi_jizhi-2024.3.5.0.dist-info/top_level.txt
cong_lingdao_yi_shenru_xuexi_qukuai_lian_gongshi_jizhi-2024.3.5.0.dist-info/RECORD
